fob/__init__.py
fob/commands/__init__.py
fob/commands/did.py
fob/commands/didnt.py
fob/commands/gm.py
fob/commands/help.py
fob/commands/info.py
fob/commands/new_month.py
fob/commands/reset.py
fob/commands/sup.py
fob/commands/overviews/__init__.py
fob/commands/overviews/day_checklist.py
fob/commands/overviews/month_overview.py
fob/db/__init__.py
fob/db/lib.py
fob/db/wrapper.py
fob/utils/__init__.py
fob/utils/utils.py
focus_blocks-0.2.12.dist-info/METADATA
focus_blocks-0.2.12.dist-info/WHEEL
focus_blocks-0.2.12.dist-info/entry_points.txt
focus_blocks-0.2.12.dist-info/licenses/LICENSE
focus_blocks-0.2.12.dist-info/RECORD
