Metadata-Version: 2.4
Name: focus-blocks
Version: 0.2.12
Summary: Focus Blocks: Simple and elegant daily time management tool.
Author-email: tensorturtle <tensorturtle@gmail.com>
License-File: LICENSE
Requires-Python: >=3.12
Requires-Dist: pytest>=8.3.4
Requires-Dist: rich>=13.9.4
Requires-Dist: tinydb>=4.8.2
